livelocals/__init__.py
livelocals/_frame.so
livelocals-1.0.0.dist-info/LICENSE
livelocals-1.0.0.dist-info/METADATA
livelocals-1.0.0.dist-info/WHEEL
livelocals-1.0.0.dist-info/top_level.txt
livelocals-1.0.0.dist-info/zip-safe
livelocals-1.0.0.dist-info/RECORD
